helper/__init__.py
helper/core.py
helper/lang/af.json
helper/lang/ak.json
helper/lang/am.json
helper/lang/ar.json
helper/lang/as.json
helper/lang/ay.json
helper/lang/az.json
helper/lang/be.json
helper/lang/bg.json
helper/lang/bho.json
helper/lang/bm.json
helper/lang/bn.json
helper/lang/bs.json
helper/lang/ca.json
helper/lang/ceb.json
helper/lang/ckb.json
helper/lang/co.json
helper/lang/cs.json
helper/lang/cy.json
helper/lang/da.json
helper/lang/de.json
helper/lang/doi.json
helper/lang/dv.json
helper/lang/ee.json
helper/lang/el.json
helper/lang/en.json
helper/lang/eo.json
helper/lang/es.json
helper/lang/et.json
helper/lang/eu.json
helper/lang/fa.json
helper/lang/fi.json
helper/lang/fr.json
helper/lang/fy.json
helper/lang/ga.json
helper/lang/gd.json
helper/lang/gl.json
helper/lang/gn.json
helper/lang/gom.json
helper/lang/gu.json
helper/lang/ha.json
helper/lang/haw.json
helper/lang/hi.json
helper/lang/hmn.json
helper/lang/hr.json
helper/lang/ht.json
helper/lang/hu.json
helper/lang/hy.json
helper/lang/id.json
helper/lang/ig.json
helper/lang/ilo.json
helper/lang/is.json
helper/lang/it.json
helper/lang/iw.json
helper/lang/ja.json
helper/lang/jw.json
helper/lang/ka.json
helper/lang/kk.json
helper/lang/km.json
helper/lang/kn.json
helper/lang/ko.json
helper/lang/kri.json
helper/lang/ku.json
helper/lang/ky.json
helper/lang/la.json
helper/lang/lb.json
helper/lang/lg.json
helper/lang/ln.json
helper/lang/lo.json
helper/lang/lt.json
helper/lang/lus.json
helper/lang/lv.json
helper/lang/mai.json
helper/lang/mg.json
helper/lang/mi.json
helper/lang/mk.json
helper/lang/ml.json
helper/lang/mn.json
helper/lang/mr.json
helper/lang/ms.json
helper/lang/mt.json
helper/lang/my.json
helper/lang/ne.json
helper/lang/nl.json
helper/lang/no.json
helper/lang/nso.json
helper/lang/ny.json
helper/lang/om.json
helper/lang/or.json
helper/lang/pa.json
helper/lang/pl.json
helper/lang/ps.json
helper/lang/pt.json
helper/lang/qu.json
helper/lang/ro.json
helper/lang/ru.json
helper/lang/rw.json
pyhelper_tools_jbhm-3.1.1.dist-info/licenses/LICENSE
pyhelper_tools_jbhm-3.1.1.dist-info/METADATA
pyhelper_tools_jbhm-3.1.1.dist-info/WHEEL
pyhelper_tools_jbhm-3.1.1.dist-info/top_level.txt
pyhelper_tools_jbhm-3.1.1.dist-info/RECORD
