Metadata-Version: 2.4
Name: pyhelper-tools-jbhm
Version: 3.1.1
Summary: A centralized toolkit for Python developers
Author: Juan Braian Hernandez Morani
Requires-Python: >=3.8
License-File: LICENSE
Requires-Dist: PyPDF2
Requires-Dist: SQLAlchemy
Requires-Dist: geopandas
Requires-Dist: ipython
Requires-Dist: matplotlib
Requires-Dist: numpy
Requires-Dist: pandas
Requires-Dist: psutil
Requires-Dist: psycopg2-binary
Requires-Dist: pyodbc
Requires-Dist: scikit-learn
Requires-Dist: scipy
Requires-Dist: seaborn
Requires-Dist: stdlib-list
Provides-Extra: linux
Requires-Dist: pyamdgpuinfo; extra == "linux"
Provides-Extra: windows
Requires-Dist: wmi; extra == "windows"
Requires-Dist: tables; extra == "windows"
Provides-Extra: macos
Dynamic: author
Dynamic: description
Dynamic: description-content-type
Dynamic: license-file
Dynamic: provides-extra
Dynamic: requires-dist
Dynamic: requires-python
Dynamic: summary
